example.cpython-311-aarch64-linux-gnu.so
pyvsag_test_jc.libs/libvsag-cf78de8f.so
pyvsag_test_jc.libs/libaio-db543aab.so.1.0.1
pyvsag_test_jc.libs/libgfortran-daac5196.so.5.0.0
pyvsag_test_jc.libs/libgomp-d22c30c5.so.1.0.0
pyvsag_test_jc-3.0.0.dist-info/RECORD
pyvsag_test_jc-3.0.0.dist-info/WHEEL
pyvsag_test_jc-3.0.0.dist-info/top_level.txt
pyvsag_test_jc-3.0.0.dist-info/METADATA
pyvsag/_version.py.in
pyvsag/_version.py
pyvsag/_pyvsag.cpython-311-aarch64-linux-gnu.so
pyvsag/__init__.py
