Metadata-Version: 2.1
Name: pyvsag_test_jc
Version: 3.0.0
Summary: vsag is a vector indexing library used for similarity search
Author-email: the vsag project <the.vsag.project@gmail.com>
License: Apache-2.0
Project-URL: Homepage, https://github.com/antgroup/vsag
Keywords: search,nearest,neighbors
Classifier: License :: OSI Approved :: Apache Software License
Classifier: Programming Language :: Python :: 3
Classifier: Programming Language :: Python :: 3.6
Classifier: Programming Language :: Python :: 3.7
Classifier: Programming Language :: Python :: 3.8
Classifier: Programming Language :: Python :: 3.9
Classifier: Programming Language :: Python :: 3.10
Classifier: Programming Language :: Python :: 3.11
Classifier: Programming Language :: Python :: 3.12
Requires-Dist: packaging
